{"precinct":"25th Precinct","month":"December","violations":[{"name":"Backing Unsafely","mtd":1,"ytd":5},{"name":"Brake Lights (Defect.or Improper)","mtd":17,"ytd":270},{"name":"Bus Lane, Driving in","mtd":0,"ytd":1},{"name":"Cell Phone","mtd":82,"ytd":1683},{"name":"Commercial Veh on Pkwy","mtd":5,"ytd":6},{"name":"Defective Brakes","mtd":0,"ytd":14},{"name":"Disobey Sign","mtd":23,"ytd":168},{"name":"Equipment (Other)","mtd":4,"ytd":56},{"name":"Fail to Keep Right","mtd":0,"ytd":0},{"name":"Fail to Signal","mtd":7,"ytd":52},{"name":"Fail to Stop on Signal","mtd":0,"ytd":37},{"name":"Following Too Closely","mtd":0,"ytd":1},{"name":"Headlights (Defect. or Improper)","mtd":18,"ytd":198},{"name":"Improper Lights","mtd":0,"ytd":0},{"name":"Improper Passing","mtd":0,"ytd":0},{"name":"Improper Turn","mtd":163,"ytd":999},{"name":"Improper/Missing Plates","mtd":3,"ytd":45},{"name":"Not Giving R of W to Pedes.","mtd":15,"ytd":196},{"name":"Not Giving R of W to Veh.","mtd":1,"ytd":1},{"name":"One Way Street","mtd":3,"ytd":54},{"name":"Pavement Markings","mtd":20,"ytd":254},{"name":"Safety Belt","mtd":113,"ytd":1862},{"name":"School Bus, Passing Stopped","mtd":0,"ytd":47},{"name":"Speeding","mtd":0,"ytd":33},{"name":"Spillback","mtd":1,"ytd":5},{"name":"Tinted Windows","mtd":0,"ytd":93},{"name":"Truck Routes","mtd":16,"ytd":269},{"name":"U-Turn","mtd":1,"ytd":3},{"name":"Uninspected","mtd":2,"ytd":40},{"name":"Uninsured","mtd":10,"ytd":127},{"name":"Unlicensed Operator","mtd":26,"ytd":283},{"name":"Unregistered","mtd":6,"ytd":56},{"name":"Unsafe Lane Change","mtd":1,"ytd":46},{"name":"Other Movers","mtd":37,"ytd":373}]}