{"precinct":"43rd Precinct","month":"   March","violations":[{"name":"Backing Unsafely","mtd":1,"ytd":14},{"name":"Brake Lights (Defect.or Improper)","mtd":44,"ytd":113},{"name":"Bus Lane, Driving in","mtd":0,"ytd":0},{"name":"Cell Phone","mtd":77,"ytd":136},{"name":"Commercial Veh on Pkwy","mtd":0,"ytd":0},{"name":"Defective Brakes","mtd":0,"ytd":0},{"name":"Disobey Sign","mtd":70,"ytd":163},{"name":"Equipment (Other)","mtd":2,"ytd":6},{"name":"Fail to Keep Right","mtd":1,"ytd":4},{"name":"Fail to Signal","mtd":61,"ytd":147},{"name":"Fail to Stop on Signal","mtd":25,"ytd":59},{"name":"Following Too Closely","mtd":0,"ytd":1},{"name":"Headlights (Defect. or Improper)","mtd":32,"ytd":95},{"name":"Improper Lights","mtd":1,"ytd":6},{"name":"Improper Passing","mtd":2,"ytd":10},{"name":"Improper Turn","mtd":99,"ytd":205},{"name":"Improper/Missing Plates","mtd":25,"ytd":49},{"name":"Not Giving R of W to Pedes.","mtd":28,"ytd":98},{"name":"Not Giving R of W to Veh.","mtd":7,"ytd":18},{"name":"One Way Street","mtd":3,"ytd":6},{"name":"Pavement Markings","mtd":35,"ytd":63},{"name":"Safety Belt","mtd":96,"ytd":152},{"name":"School Bus, Passing Stopped","mtd":0,"ytd":1},{"name":"Speeding","mtd":31,"ytd":77},{"name":"Spillback","mtd":1,"ytd":6},{"name":"Tinted Windows","mtd":169,"ytd":515},{"name":"Truck Routes","mtd":0,"ytd":1},{"name":"U-Turn","mtd":7,"ytd":14},{"name":"Uninspected","mtd":0,"ytd":1},{"name":"Uninsured","mtd":26,"ytd":69},{"name":"Unlicensed Operator","mtd":70,"ytd":171},{"name":"Unregistered","mtd":13,"ytd":22},{"name":"Unsafe Lane Change","mtd":13,"ytd":29},{"name":"Other Movers","mtd":55,"ytd":92}]}